<?xml version="1.0" encoding="utf-8"?><index><!-- saved from url=(0014)about:internet -->
<stem n="bandwidth"><phr n="bandwidth"><ent r="3" t="16" w="169" /><ent r="8" t="18" w="339" /><ent r="8" t="18" w="386" /><ent r="8" t="18" w="401" /></phr></stem><stem n="intf0"><phr n="intf0"><ent r="3" t="16" w="174" /><ent r="6" t="16" w="261" /><ent r="5" t="16" w="492" /><ent r="5" t="16" w="539" /><ent r="8" t="16" w="711" /><ent r="7" t="17" w="135" /><ent r="8" t="17" w="148" /><ent r="7" t="18" w="267" /><ent r="8" t="18" w="280" /><ent r="7" t="19" w="242" /><ent r="3" t="21" w="28" /><ent r="8" t="28" w="146" /></phr></stem><stem n="(intf0,"><phr n="(intf0,"><ent r="3" t="16" w="175" /><ent r="7" t="17" w="136" /><ent r="7" t="18" w="268" /><ent r="7" t="19" w="243" /><ent r="3" t="21" w="29" /></phr></stem><stem n="intf1"><phr n="intf1"><ent r="3" t="16" w="175" /><ent r="6" t="16" w="266" /><ent r="5" t="16" w="499" /><ent r="5" t="16" w="546" /><ent r="8" t="16" w="727" /><ent r="7" t="17" w="136" /><ent r="8" t="17" w="153" /><ent r="7" t="18" w="268" /><ent r="8" t="18" w="285" /><ent r="7" t="19" w="243" /><ent r="3" t="21" w="29" /><ent r="8" t="28" w="148" /></phr></stem><stem n="intf2"><phr n="intf2"><ent r="3" t="16" w="176" /><ent r="6" t="16" w="270" /><ent r="5" t="16" w="506" /><ent r="5" t="16" w="553" /><ent r="8" t="16" w="742" /><ent r="7" t="17" w="137" /><ent r="8" t="17" w="157" /><ent r="7" t="18" w="269" /><ent r="8" t="18" w="289" /><ent r="7" t="19" w="244" /><ent r="3" t="21" w="30" /><ent r="8" t="28" w="150" /></phr></stem><stem n="identifi"><phr n="identified"><ent r="3" t="16" w="181" /><ent r="7" t="17" w="142" /><ent r="7" t="18" w="274" /><ent r="7" t="19" w="249" /></phr><phr n="identify"><ent r="6" t="21" w="471" /><ent r="8" t="24" w="308" /><ent r="8" t="25" w="370" /><ent r="8" t="26" w="293" /><ent r="8" t="27" w="300" /><ent r="4" t="30" w="120" /><ent r="8" t="31" w="150" /><ent r="8" t="32" w="267" /></phr><phr n="identifies"><ent r="8" t="24" w="269" /><ent r="8" t="25" w="336" /><ent r="8" t="26" w="259" /><ent r="8" t="27" w="266" /><ent r="6" t="56" w="111" /></phr><phr n="identifier"><ent r="6" t="36" w="178" /><ent r="6" t="56" w="128" /></phr></stem><stem n="(admin,"><phr n="(admin,"><ent r="3" t="16" w="183" /><ent r="6" t="16" w="263" /><ent r="8" t="16" w="713" /><ent r="7" t="17" w="144" /><ent r="8" t="17" w="150" /><ent r="7" t="18" w="276" /><ent r="8" t="18" w="282" /><ent r="7" t="19" w="251" /><ent r="3" t="21" w="36" /><ent r="7" t="28" w="430" /></phr></stem><stem n="os_sdn,"><phr n="os_sdn,"><ent r="3" t="16" w="184" /><ent r="3" t="16" w="183" /><ent r="5" t="16" w="523" /><ent r="5" t="16" w="522" /><ent r="7" t="17" w="145" /><ent r="7" t="17" w="144" /><ent r="7" t="18" w="277" /><ent r="7" t="18" w="276" /><ent r="7" t="19" w="252" /><ent r="7" t="19" w="251" /><ent r="3" t="21" w="37" /><ent r="3" t="21" w="36" /><ent r="4" t="21" w="183" /><ent r="4" t="21" w="182" /><ent r="7" t="32" w="101" /><ent r="7" t="32" w="100" /><ent r="8" t="32" w="117" /><ent r="8" t="32" w="116" /></phr></stem><stem n="_sdn,"><phr n="_sdn,"><ent r="3" t="16" w="185" /><ent r="5" t="16" w="524" /><ent r="7" t="17" w="146" /><ent r="7" t="18" w="278" /><ent r="7" t="19" w="253" /><ent r="3" t="21" w="38" /><ent r="4" t="21" w="184" /><ent r="7" t="32" w="102" /><ent r="8" t="32" w="118" /></phr></stem><stem n="public"><phr n="public"><ent r="3" t="16" w="185" /><ent r="6" t="16" w="271" /><ent r="5" t="16" w="426" /><ent r="5" t="16" w="477" /><ent r="5" t="16" w="525" /><ent r="8" t="16" w="743" /><ent r="7" t="17" w="146" /><ent r="8" t="17" w="158" /><ent r="7" t="18" w="278" /><ent r="8" t="18" w="290" /><ent r="7" t="19" w="253" /><ent r="3" t="21" w="39" /><ent r="3" t="21" w="67" /><ent r="3" t="21" w="73" /><ent r="3" t="21" w="108" /><ent r="4" t="21" w="185" /><ent r="5" t="21" w="224" /><ent r="9" t="22" w="152" /><ent r="7" t="22" w="274" /><ent r="7" t="22" w="322" /><ent r="7" t="23" w="178" /><ent r="7" t="23" w="184" /><ent r="7" t="23" w="210" /><ent r="7" t="23" w="216" /><ent r="7" t="23" w="247" /><ent r="6" t="23" w="293" /><ent r="7" t="23" w="334" /><ent r="7" t="23" w="376" /><ent r="3" t="24" w="42" /><ent r="3" t="27" w="42" /><ent r="3" t="27" w="142" /><ent r="6" t="27" w="159" /><ent r="6" t="27" w="173" /><ent r="7" t="27" w="198" /><ent r="9" t="28" w="288" /><ent r="9" t="28" w="349" /><ent r="7" t="28" w="430" /><ent r="7" t="32" w="103" /><ent r="8" t="32" w="119" /></phr><phr n="Public"><ent r="8" t="22" w="154" /><ent r="65" t="24" w="340" /><ent r="1000" t="27" w="1" /><ent r="102" t="27" w="8" /></phr><phr n="Publication"><ent r="7" t="48" w="229" /></phr></stem><stem n="stand"><phr n="stands"><ent r="3" t="16" w="190" /></phr></stem><stem n="openstack"><phr n="OpenStack"><ent r="3" t="16" w="192" /><ent r="8" t="22" w="119" /><ent r="7" t="36" w="402" /></phr></stem><stem n="softwar"><phr n="Software"><ent r="3" t="16" w="193" /><ent r="8" t="22" w="120" /></phr><phr n="software"><ent r="7" t="32" w="192" /><ent r="3" t="46" w="17" /></phr></stem><stem n="software-defin"><phr n="Software-Defined"><ent r="3" t="16" w="193" /><ent r="8" t="22" w="120" /></phr></stem><stem n="software-defined-network"><phr n="Software-Defined-Network"><ent r="3" t="16" w="193" /><ent r="8" t="22" w="120" /></phr></stem><stem n="defined-network"><phr n="Defined-Network"><ent r="3" t="16" w="194" /><ent r="8" t="22" w="121" /></phr></stem><stem n="-defined-network."><phr n="-Defined-Network."><ent r="3" t="16" w="196" /><ent r="3" t="16" w="197" /><ent r="8" t="22" w="123" /><ent r="8" t="22" w="124" /></phr></stem><stem n="singl"><phr n="Single"><ent r="6" t="16" w="202" /><ent r="4" t="16" w="561" /><ent r="8" t="17" w="51" /></phr><phr n="single"><ent r="6" t="16" w="252" /><ent r="8" t="17" w="101" /><ent r="8" t="22" w="302" /><ent r="8" t="23" w="395" /><ent r="10" t="28" w="377" /><ent r="8" t="32" w="91" /><ent r="7" t="42" w="142" /><ent r="6" t="42" w="203" /><ent r="6" t="42" w="259" /><ent r="6" t="42" w="309" /><ent r="8" t="43" w="262" /></phr></stem><stem n="share"><phr n="shared"><ent r="6" t="16" w="207" /><ent r="6" t="16" w="236" /><ent r="8" t="17" w="56" /><ent r="8" t="17" w="85" /><ent r="4" t="40" w="172" /></phr></stem><stem n="through"><phr n="through"><ent r="6" t="16" w="213" /><ent r="6" t="16" w="243" /><ent r="8" t="17" w="62" /><ent r="8" t="17" w="92" /><ent r="3" t="35" w="22" /><ent r="7" t="36" w="213" /><ent r="6" t="41" w="129" /><ent r="6" t="42" w="624" /><ent r="7" t="43" w="463" /></phr></stem><stem n="vlan"><phr n="VLAN"><ent r="6" t="16" w="214" /><ent r="6" t="16" w="225" /><ent r="6" t="16" w="244" /><ent r="6" t="16" w="641" /><ent r="8" t="17" w="63" /><ent r="8" t="17" w="74" /><ent r="8" t="17" w="93" /><ent r="8" t="22" w="107" /><ent r="8" t="22" w="110" /><ent r="7" t="22" w="231" /><ent r="7" t="22" w="247" /><ent r="7" t="22" w="282" /><ent r="7" t="22" w="328" /><ent r="7" t="23" w="265" /><ent r="7" t="23" w="268" /><ent r="7" t="23" w="296" /><ent r="7" t="28" w="231" /><ent r="7" t="28" w="234" /><ent r="7" t="28" w="251" /><ent r="9" t="28" w="294" /><ent r="9" t="28" w="357" /></phr><phr n="vlan"><ent r="6" t="16" w="264" /><ent r="8" t="16" w="714" /><ent r="8" t="17" w="151" /><ent r="8" t="18" w="283" /><ent r="9" t="22" w="102" /></phr><phr n="VLANs"><ent r="4" t="16" w="580" /></phr></stem><stem n="dual"><phr n="Dual"><ent r="6" t="16" w="216" /><ent r="5" t="16" w="299" /><ent r="5" t="16" w="400" /><ent r="5" t="16" w="442" /><ent r="8" t="17" w="65" /><ent r="4" t="21" w="169" /></phr><phr n="dual"><ent r="8" t="22" w="348" /><ent r="8" t="23" w="351" /><ent r="10" t="28" w="314" /><ent r="9" t="32" w="132" /></phr></stem><stem n="their"><phr n="their"><ent r="6" t="16" w="221" /><ent r="5" t="16" w="411" /><ent r="8" t="17" w="70" /><ent r="7" t="36" w="249" /></phr></stem><stem n="own"><phr n="own"><ent r="6" t="16" w="222" /><ent r="8" t="17" w="71" /><ent r="5" t="21" w="235" /><ent r="4" t="40" w="156" /></phr></stem><stem n="where"><phr n="where"><ent r="6" t="16" w="224" /><ent r="8" t="17" w="73" /><ent r="7" t="31" w="55" /><ent r="8" t="36" w="260" /><ent r="3" t="40" w="108" /><ent r="6" t="52" w="240" /><ent r="6" t="53" w="116" /></phr></stem><stem n="bridg"><phr n="bridge"><ent r="6" t="16" w="227" /><ent r="8" t="17" w="76" /><ent r="6" t="22" w="369" /><ent r="7" t="23" w="227" /><ent r="9" t="28" w="203" /><ent r="8" t="28" w="219" /></phr><phr n="Bridge"><ent r="7" t="22" w="361" /><ent r="7" t="23" w="221" /><ent r="7" t="28" w="184" /></phr></stem><stem n="off"><phr n="off"><ent r="6" t="16" w="229" /><ent r="8" t="17" w="78" /></phr><phr n="Off"><ent r="9" t="36" w="267" /></phr></stem><stem n="team"><phr n="Team"><ent r="6" t="16" w="231" /><ent r="5" t="16" w="598" /><ent r="6" t="16" w="692" /><ent r="8" t="17" w="80" /><ent r="6" t="18" w="236" /><ent r="7" t="18" w="489" /><ent r="6" t="19" w="210" /><ent r="6" t="19" w="343" /></phr><phr n="Teaming"><ent r="6" t="16" w="245" /><ent r="8" t="17" w="94" /></phr><phr n="teaming"><ent r="6" t="16" w="677" /><ent r="7" t="17" w="205" /><ent r="7" t="18" w="443" /><ent r="7" t="18" w="460" /><ent r="7" t="18" w="472" /><ent r="6" t="19" w="301" /><ent r="6" t="19" w="318" /><ent r="6" t="19" w="330" /></phr><phr n="team"><ent r="7" t="17" w="220" /><ent r="8" t="32" w="95" /></phr></stem><stem n="two"><phr n="two"><ent r="6" t="16" w="240" /><ent r="8" t="17" w="89" /></phr></stem><stem n="mean"><phr n="means"><ent r="6" t="16" w="246" /><ent r="5" t="16" w="307" /><ent r="5" t="16" w="368" /><ent r="8" t="17" w="95" /><ent r="7" t="18" w="179" /><ent r="7" t="19" w="154" /><ent r="7" t="22" w="292" /><ent r="7" t="22" w="338" /><ent r="7" t="23" w="341" /><ent r="7" t="23" w="385" /><ent r="9" t="28" w="304" /><ent r="9" t="28" w="367" /></phr><phr n="meaning"><ent r="8" t="18" w="336" /></phr></stem><stem n="treat"><phr n="treating"><ent r="6" t="16" w="247" /><ent r="8" t="17" w="96" /></phr></stem><stem n="wire"><phr n="wires"><ent r="6" t="16" w="249" /><ent r="8" t="17" w="98" /></phr><phr n="wired"><ent r="5" t="16" w="413" /><ent r="5" t="21" w="221" /></phr><phr n="wiring"><ent r="5" t="16" w="446" /></phr></stem><stem n="bundl"><phr n="bundle"><ent r="6" t="16" w="253" /><ent r="8" t="17" w="102" /></phr></stem><stem n="bmc"><phr n="bmc"><ent r="6" t="16" w="263" /><ent r="8" t="16" w="713" /><ent r="8" t="17" w="150" /><ent r="8" t="18" w="282" /><ent r="9" t="22" w="82" /><ent r="9" t="22" w="101" /><ent r="8" t="28" w="144" /></phr><phr n="BMC"><ent r="7" t="31" w="217" /><ent r="6" t="31" w="225" /><ent r="7" t="32" w="136" /><ent r="8" t="32" w="148" /><ent r="7" t="32" w="164" /><ent r="6" t="32" w="177" /></phr></stem><stem n="bmc_vlan"><phr n="bmc_vlan"><ent r="6" t="16" w="264" /><ent r="6" t="16" w="263" /><ent r="8" t="16" w="714" /><ent r="8" t="16" w="713" /><ent r="8" t="17" w="151" /><ent r="8" t="17" w="150" /><ent r="8" t="18" w="283" /><ent r="8" t="18" w="282" /><ent r="9" t="22" w="102" /><ent r="9" t="22" w="101" /></phr></stem><stem n="_vlan)"><phr n="_vlan)"><ent r="6" t="16" w="265" /><ent r="8" t="16" w="715" /><ent r="8" t="17" w="152" /><ent r="8" t="18" w="284" /></phr></stem><stem n="(os_sdn)"><phr n="(os_sdn)"><ent r="6" t="16" w="269" /><ent r="8" t="16" w="730" /><ent r="8" t="17" w="156" /><ent r="8" t="18" w="288" /></phr></stem><stem n="(public)"><phr n="(public)"><ent r="6" t="16" w="272" /><ent r="8" t="16" w="744" /><ent r="8" t="17" w="159" /><ent r="8" t="18" w="291" /></phr></stem><stem n="1gb"><phr n="1Gb"><ent r="6" t="16" w="279" /><ent r="6" t="16" w="285" /><ent r="6" t="16" w="291" /><ent r="5" t="16" w="302" /><ent r="5" t="16" w="344" /><ent r="5" t="16" w="374" /><ent r="5" t="16" w="493" /><ent r="5" t="16" w="500" /><ent r="5" t="16" w="507" /><ent r="5" t="16" w="540" /><ent r="5" t="16" w="547" /><ent r="5" t="16" w="554" /><ent r="8" t="16" w="716" /><ent r="8" t="16" w="720" /><ent r="8" t="16" w="731" /><ent r="8" t="16" w="735" /><ent r="8" t="16" w="745" /><ent r="8" t="16" w="749" /></phr></stem><stem n="prefer"><phr n="preferred"><ent r="6" t="16" w="280" /><ent r="6" t="16" w="286" /><ent r="6" t="16" w="292" /><ent r="5" t="16" w="303" /><ent r="5" t="16" w="333" /><ent r="5" t="16" w="365" /><ent r="5" t="16" w="494" /><ent r="5" t="16" w="501" /><ent r="5" t="16" w="508" /><ent r="5" t="16" w="541" /><ent r="5" t="16" w="548" /><ent r="5" t="16" w="555" /><ent r="9" t="18" w="333" /></phr><phr n="Preference"><ent r="7" t="23" w="446" /><ent r="7" t="28" w="411" /><ent r="7" t="28" w="484" /></phr><phr n="preference"><ent r="7" t="28" w="417" /></phr><phr n="prefer"><ent r="3" t="40" w="111" /></phr></stem><stem n="(preferred)"><phr n="(preferred)"><ent r="6" t="16" w="281" /><ent r="6" t="16" w="287" /><ent r="6" t="16" w="293" /><ent r="5" t="16" w="304" /><ent r="5" t="16" w="495" /><ent r="5" t="16" w="502" /><ent r="5" t="16" w="509" /><ent r="5" t="16" w="542" /><ent r="5" t="16" w="549" /><ent r="5" t="16" w="556" /></phr></stem><stem n="1st"><phr n="1st"><ent r="6" t="16" w="282" /><ent r="5" t="16" w="496" /><ent r="5" t="16" w="543" /><ent r="8" t="16" w="718" /><ent r="8" t="16" w="733" /><ent r="8" t="16" w="747" /><ent r="8" t="18" w="316" /></phr></stem><stem n="2nd"><phr n="2nd"><ent r="6" t="16" w="288" /><ent r="5" t="16" w="305" /><ent r="5" t="16" w="510" /><ent r="8" t="16" w="722" /><ent r="8" t="16" w="737" /><ent r="8" t="16" w="751" /><ent r="8" t="18" w="366" /></phr></stem><stem n="3rd"><phr n="3rd"><ent r="6" t="16" w="294" /><ent r="5" t="16" w="503" /><ent r="5" t="16" w="550" /><ent r="8" t="18" w="388" /></phr></stem><stem n="&quot;1gb"><phr n="&quot;1Gb"><ent r="5" t="16" w="302" /></phr></stem><stem n="gigabit"><phr n="gigabit"><ent r="5" t="16" w="310" /></phr><phr n="gigabits"><ent r="8" t="18" w="405" /></phr></stem><stem n="'s"><phr n="'s"><ent r="5" t="16" w="322" /><ent r="6" t="16" w="685" /><ent r="3" t="24" w="316" /><ent r="3" t="35" w="57" /><ent r="4" t="36" w="31" /><ent r="7" t="36" w="146" /><ent r="6" t="36" w="176" /><ent r="6" t="36" w="187" /><ent r="7" t="42" w="406" /><ent r="6" t="42" w="513" /><ent r="6" t="42" w="537" /><ent r="6" t="42" w="561" /><ent r="6" t="42" w="567" /><ent r="3" t="43" w="46" /><ent r="7" t="43" w="480" /><ent r="6" t="49" w="93" /></phr></stem><stem n="server'"><phr n="server's"><ent r="5" t="16" w="322" /><ent r="5" t="16" w="321" /><ent r="4" t="36" w="31" /><ent r="4" t="36" w="30" /></phr></stem><stem n="bio"><phr n="BIOS"><ent r="5" t="16" w="323" /></phr></stem><stem n="overridden"><phr n="overridden"><ent r="5" t="16" w="326" /></phr></stem><stem n="&quot;preferred&quot;"><phr n="&quot;preferred&quot;"><ent r="5" t="16" w="334" /></phr></stem><stem n="tag"><phr n="tag"><ent r="5" t="16" w="334" /><ent r="5" t="16" w="366" /></phr><phr n="tagged"><ent r="4" t="16" w="579" /></phr></stem><stem n="suggest"><phr n="suggests"><ent r="5" t="16" w="335" /></phr></stem><stem n="nic"><phr n="NIC"><ent r="5" t="16" w="339" /><ent r="5" t="16" w="357" /><ent r="6" t="16" w="678" /><ent r="6" t="16" w="681" /><ent r="8" t="18" w="346" /><ent r="8" t="18" w="435" /><ent r="7" t="36" w="151" /><ent r="6" t="36" w="188" /></phr></stem><stem n="/port"><phr n="/port"><ent r="5" t="16" w="340" /></phr></stem><stem n="nic/port"><phr n="NIC/port"><ent r="5" t="16" w="340" /><ent r="5" t="16" w="339" /></phr></stem><stem n="fall"><phr n="falls"><ent r="5" t="16" w="347" /></phr><phr n="fall"><ent r="5" t="21" w="277" /></phr></stem><stem n="back"><phr n="back"><ent r="5" t="16" w="348" /><ent r="3" t="40" w="76" /></phr></stem><stem n="next"><phr n="next"><ent r="5" t="16" w="351" /><ent r="4" t="16" w="584" /><ent r="8" t="18" w="363" /><ent r="6" t="49" w="154" /></phr><phr n="Next"><ent r="4" t="42" w="646" /><ent r="4" t="43" w="525" /></phr></stem><stem n="maximum"><phr n="maximum"><ent r="5" t="16" w="352" /><ent r="6" t="42" w="430" /><ent r="8" t="44" w="182" /><ent r="6" t="55" w="74" /></phr><phr n="Maximum"><ent r="7" t="42" w="422" /><ent r="9" t="44" w="172" /></phr></stem><stem n="speed"><phr n="speed"><ent r="5" t="16" w="353" /></phr></stem><stem n="there"><phr n="there"><ent r="5" t="16" w="362" /><ent r="6" t="21" w="432" /><ent r="4" t="30" w="74" /><ent r="8" t="31" w="104" /><ent r="8" t="32" w="221" /></phr><phr n="There"><ent r="3" t="40" w="30" /><ent r="3" t="40" w="103" /></phr></stem><stem n=";"><phr n=";"><ent r="5" t="16" w="375" /><ent r="5" t="16" w="476" /><ent r="5" t="16" w="480" /><ent r="6" t="16" w="642" /><ent r="8" t="18" w="406" /><ent r="8" t="18" w="409" /><ent r="4" t="21" w="180" /></phr></stem><stem n="otherwis"><phr n="otherwise"><ent r="5" t="16" w="375" /></phr><phr n="Otherwise"><ent r="6" t="21" w="402" /></phr></stem><stem n="deploy"><phr n="deployment"><ent r="5" t="16" w="377" /><ent r="5" t="21" w="203" /><ent r="7" t="28" w="428" /><ent r="3" t="35" w="71" /><ent r="7" t="36" w="248" /></phr></stem><stem n="succe"><phr n="succeed"><ent r="5" t="16" w="380" /></phr></stem><stem n="criteria"><phr n="criteria"><ent r="3" t="16" w="387" /><ent r="3" t="21" w="154" /></phr></stem><stem n="consid"><phr n="considered"><ent r="3" t="16" w="390" /><ent r="3" t="21" w="157" /><ent r="4" t="25" w="28" /><ent r="6" t="42" w="202" /></phr></stem><stem n="assum"><phr n="assume"><ent r="5" t="16" w="405" /><ent r="4" t="21" w="170" /></phr><phr n="assumed"><ent r="4" t="16" w="568" /></phr></stem><stem n="eth1"><phr n="eth1"><ent r="5" t="16" w="420" /><ent r="5" t="16" w="476" /><ent r="6" t="16" w="620" /><ent r="6" t="16" w="636" /></phr></stem><stem n="eth2"><phr n="eth2"><ent r="5" t="16" w="425" /><ent r="5" t="16" w="478" /><ent r="5" t="16" w="521" /><ent r="6" t="16" w="612" /><ent r="6" t="16" w="648" /></phr></stem><stem n="/extern"><phr n="/external"><ent r="5" t="16" w="427" /><ent r="5" t="16" w="526" /></phr></stem><stem n="public/extern"><phr n="public/external"><ent r="5" t="16" w="427" /><ent r="5" t="16" w="426" /><ent r="5" t="16" w="526" /><ent r="5" t="16" w="525" /></phr></stem><stem n="import"><phr n="IMPORTANT"><ent r="6" t="16" w="430" /></phr><phr n="Important"><ent r="4" t="21" w="104" /><ent r="9" t="42" w="152" /></phr><phr n="Import"><ent r="65" t="45" w="37" /><ent r="7" t="47" w="263" /><ent r="67" t="47" w="273" /><ent r="1000" t="49" w="1" /><ent r="102" t="49" w="5" /><ent r="4" t="49" w="28" /><ent r="3" t="49" w="43" /><ent r="7" t="49" w="109" /></phr><phr n="Imported"><ent r="7" t="47" w="124" /></phr><phr n="imported"><ent r="6" t="47" w="138" /><ent r="7" t="48" w="125" /><ent r="6" t="49" w="83" /></phr><phr n="import"><ent r="6" t="49" w="132" /></phr></stem><stem n="scenario"><phr n="scenario"><ent r="6" t="16" w="434" /></phr></stem><stem n="intact"><phr n="intact"><ent r="6" t="16" w="439" /></phr></stem><stem n="between"><phr n="between"><ent r="5" t="16" w="449" /><ent r="8" t="18" w="421" /><ent r="3" t="21" w="53" /><ent r="3" t="21" w="81" /><ent r="8" t="22" w="129" /><ent r="7" t="23" w="421" /><ent r="6" t="28" w="405" /><ent r="4" t="40" w="173" /></phr></stem><stem n="-contigu"><phr n="-contiguous"><ent r="5" t="16" w="453" /><ent r="5" t="16" w="453" /></phr></stem><stem n="non-contigu"><phr n="non-contiguous"><ent r="5" t="16" w="453" /></phr></stem><stem n="contigu"><phr n="contiguous"><ent r="5" t="16" w="454" /></phr></stem><stem n="/or"><phr n="/or"><ent r="5" t="16" w="456" /></phr></stem><stem n="and/or"><phr n="and/or"><ent r="5" t="16" w="456" /><ent r="5" t="16" w="455" /></phr></stem><stem n="sequenc"><phr n="sequence"><ent r="5" t="16" w="459" /></phr></stem><stem n="map"><phr n="mapping"><ent r="5" t="16" w="466" /><ent r="6" t="16" w="588" /></phr><phr n="Map"><ent r="6" t="16" w="610" /><ent r="6" t="16" w="619" /></phr></stem><stem n="privat"><phr n="private"><ent r="5" t="16" w="479" /><ent r="8" t="22" w="79" /><ent r="8" t="22" w="149" /><ent r="8" t="23" w="438" /><ent r="4" t="25" w="33" /></phr></stem><stem n="look"><phr n="look"><ent r="5" t="16" w="487" /><ent r="5" t="16" w="534" /><ent r="6" t="16" w="696" /></phr></stem><stem n="eth4"><phr n="eth4"><ent r="5" t="16" w="524" /><ent r="6" t="16" w="614" /><ent r="6" t="16" w="654" /></phr></stem><stem n="5th"><phr n="5th"><ent r="5" t="16" w="557" /></phr></stem><stem n="switch"><phr n="switch"><ent r="4" t="16" w="576" /><ent r="8" t="25" w="273" /></phr><phr n="switches"><ent r="5" t="21" w="212" /></phr></stem><stem n="(discuss"><phr n="(discussed"><ent r="4" t="16" w="581" /></phr></stem><stem n="discuss"><phr n="discussed"><ent r="4" t="16" w="581" /></phr></stem><stem n="ident"><phr n="identical"><ent r="6" t="16" w="591" /></phr><phr n="identity"><ent r="6" t="42" w="228" /></phr></stem><stem n="virtual"><phr n="virtual"><ent r="5" t="16" w="601" /><ent r="4" t="35" w="84" /><ent r="4" t="36" w="26" /></phr><phr n="Virtual"><ent r="3" t="21" w="83" /><ent r="8" t="22" w="131" /><ent r="8" t="22" w="190" /><ent r="6" t="22" w="235" /><ent r="6" t="23" w="271" /><ent r="6" t="28" w="239" /></phr><phr n="virtualization"><ent r="8" t="43" w="320" /></phr></stem><stem n="both"><phr n="both"><ent r="5" t="16" w="605" /><ent r="8" t="43" w="266" /><ent r="8" t="43" w="288" /></phr></stem><stem n="trunk"><phr n="trunks"><ent r="5" t="16" w="606" /></phr><phr n="trunk"><ent r="6" t="16" w="616" /><ent r="6" t="16" w="625" /></phr></stem><stem n="eth3"><phr n="eth3"><ent r="6" t="16" w="621" /><ent r="6" t="16" w="650" /></phr></stem><stem n="eth5"><phr n="eth5"><ent r="6" t="16" w="623" /><ent r="6" t="16" w="656" /></phr></stem><stem n="belong"><phr n="belongs"><ent r="6" t="16" w="638" /><ent r="6" t="38" w="234" /><ent r="6" t="38" w="279" /></phr></stem><stem n="true"><phr n="true"><ent r="6" t="16" w="645" /></phr><phr n="True"><ent r="8" t="22" w="289" /><ent r="7" t="22" w="389" /><ent r="7" t="23" w="241" /><ent r="8" t="23" w="367" /><ent r="8" t="28" w="189" /><ent r="9" t="28" w="215" /><ent r="8" t="28" w="257" /><ent r="9" t="28" w="327" /><ent r="10" t="28" w="364" /><ent r="6" t="48" w="260" /><ent r="6" t="48" w="291" /></phr></stem><stem n="pair"><phr n="pair"><ent r="6" t="16" w="651" /><ent r="6" t="16" w="657" /></phr><phr n="pairs"><ent r="6" t="16" w="682" /></phr></stem><stem n="here'"><phr n="Here's"><ent r="6" t="16" w="685" /><ent r="6" t="16" w="684" /></phr></stem><stem n="partial"><phr n="partial"><ent r="6" t="16" w="687" /></phr></stem><stem n="6"><phr n="6"><ent r="8" t="16" w="725" /><ent r="8" t="16" w="740" /><ent r="8" t="16" w="754" /><ent r="7" t="18" w="457" /><ent r="6" t="19" w="315" /></phr></stem><stem n="avail"><phr n="available"><ent r="7" t="17" w="43" /><ent r="8" t="18" w="338" /><ent r="7" t="22" w="43" /><ent r="10" t="41" w="277" /></phr></stem><stem n="role"><phr n="Role"><ent r="7" t="17" w="104" /><ent r="7" t="18" w="157" /><ent r="7" t="19" w="132" /><ent r="7" t="38" w="236" /></phr><phr n="roles"><ent r="6" t="17" w="110" /><ent r="7" t="42" w="364" /></phr><phr n="role"><ent r="7" t="18" w="182" /><ent r="7" t="19" w="157" /><ent r="3" t="35" w="67" /><ent r="7" t="38" w="242" /><ent r="6" t="42" w="519" /><ent r="6" t="42" w="543" /><ent r="6" t="42" w="568" /></phr></stem><stem n="):"><phr n="):"><ent r="7" t="17" w="147" /><ent r="7" t="18" w="279" /></phr></stem><stem n="algorithm"><phr n="algorithm"><ent r="7" t="17" w="206" /><ent r="7" t="18" w="444" /><ent r="7" t="18" w="466" /><ent r="6" t="19" w="302" /><ent r="6" t="19" w="324" /></phr></stem><stem n="bond"><phr n="bonding"><ent r="7" t="17" w="211" /><ent r="7" t="18" w="449" /><ent r="6" t="19" w="307" /></phr></stem><stem n="driver"><phr n="driver"><ent r="7" t="17" w="212" /><ent r="7" t="18" w="450" /><ent r="6" t="19" w="308" /></phr><phr n="drivers"><ent r="4" t="35" w="113" /></phr></stem><stem n="unavail"><phr n="unavailable"><ent r="8" t="17" w="320" /></phr></stem><stem n="(network"><phr n="(network"><ent r="6" t="18" w="146" /></phr></stem><stem n="indic"><phr n="Indicates"><ent r="7" t="18" w="159" /><ent r="7" t="19" w="134" /><ent r="7" t="22" w="252" /><ent r="6" t="22" w="366" /><ent r="7" t="23" w="224" /><ent r="7" t="23" w="300" /></phr><phr n="indicates"><ent r="8" t="18" w="330" /><ent r="7" t="18" w="459" /><ent r="6" t="19" w="317" /><ent r="7" t="43" w="487" /></phr><phr n="indicate"><ent r="8" t="18" w="383" /></phr><phr n="indicating"><ent r="7" t="36" w="136" /></phr></stem><stem n="specif"><phr n="specific"><ent r="7" t="18" w="166" /><ent r="7" t="19" w="141" /><ent r="7" t="19" w="285" /><ent r="6" t="44" w="201" /></phr></stem><stem n="(blank)"><phr n="(blank)"><ent r="8" t="18" w="207" /><ent r="8" t="19" w="182" /></phr></stem><stem n="releas"><phr n="release"><ent r="8" t="18" w="209" /><ent r="7" t="18" w="478" /><ent r="8" t="19" w="184" /><ent r="6" t="19" w="336" /></phr></stem><stem n="row"><phr n="row"><ent r="6" t="18" w="220" /><ent r="6" t="18" w="248" /><ent r="6" t="19" w="195" /><ent r="6" t="19" w="222" /><ent r="6" t="36" w="331" /></phr></stem><stem n="(s)."><phr n="(s)."><ent r="6" t="18" w="250" /><ent r="6" t="19" w="224" /><ent r="3" t="40" w="30" /></phr></stem><stem n="(up"><phr n="(up"><ent r="7" t="18" w="307" /><ent r="7" t="19" w="279" /></phr></stem><stem n="four"><phr n="four"><ent r="7" t="18" w="309" /><ent r="7" t="19" w="281" /></phr></stem><stem n="charact"><phr n="characters"><ent r="7" t="18" w="310" /><ent r="7" t="19" w="282" /><ent r="6" t="32" w="66" /><ent r="6" t="32" w="72" /><ent r="8" t="37" w="87" /><ent r="8" t="41" w="95" /><ent r="8" t="42" w="111" /><ent r="8" t="43" w="218" /></phr><phr n="character"><ent r="8" t="18" w="317" /><ent r="8" t="18" w="364" /><ent r="8" t="18" w="367" /><ent r="8" t="18" w="389" /><ent r="8" t="18" w="414" /><ent r="7" t="42" w="370" /><ent r="6" t="47" w="206" /><ent r="6" t="52" w="164" /></phr></stem><stem n="convent"><phr n="conventions"><ent r="7" t="18" w="314" /><ent r="7" t="19" w="286" /></phr></stem><stem n="question"><phr n="question"><ent r="8" t="18" w="323" /><ent r="8" t="18" w="328" /></phr></stem><stem n="mark"><phr n="mark"><ent r="8" t="18" w="324" /><ent r="8" t="18" w="329" /></phr></stem><stem n="(?)"><phr n="(?)"><ent r="8" t="18" w="325" /></phr></stem><stem n="card"><phr n="card"><ent r="8" t="18" w="345" /></phr></stem><stem n="(nic)."><phr n="(NIC)."><ent r="8" t="18" w="347" /></phr></stem><stem n="(blank),"><phr n="(blank),"><ent r="8" t="18" w="351" /></phr></stem><stem n="100"><phr n="100"><ent r="8" t="18" w="376" /></phr></stem><stem n="numer"><phr n="numerical"><ent r="8" t="18" w="380" /><ent r="8" t="18" w="428" /><ent r="7" t="28" w="415" /></phr></stem><stem n="g"><phr n="g"><ent r="8" t="18" w="394" /><ent r="8" t="18" w="403" /></phr></stem><stem n="m"><phr n="m"><ent r="8" t="18" w="395" /><ent r="8" t="18" w="406" /></phr></stem><stem n="k"><phr n="k"><ent r="8" t="18" w="397" /><ent r="8" t="18" w="409" /></phr></stem><stem n="unit"><phr n="unit"><ent r="8" t="18" w="402" /></phr></stem><stem n="repres"><phr n="represents"><ent r="8" t="18" w="404" /><ent r="8" t="18" w="407" /><ent r="8" t="18" w="410" /></phr><phr n="represent"><ent r="6" t="42" w="444" /></phr><phr n="representative"><ent r="7" t="56" w="188" /></phr></stem></index>